quickemcee/__init__.py
quickemcee/core.py
quickemcee/utils.py
quickemcee-0.0.1a5.dist-info/LICENSE
quickemcee-0.0.1a5.dist-info/METADATA
quickemcee-0.0.1a5.dist-info/WHEEL
quickemcee-0.0.1a5.dist-info/top_level.txt
quickemcee-0.0.1a5.dist-info/RECORD
