Metadata-Version: 2.1
Name: quickemcee
Version: 0.0.1a5
Summary: quickemcee is a library with built in scriptsusing the emcee library to quickly set up MCMC analysis.
Home-page: https://github.com/sofia-scz/quick-emcee/
Author: Sofia A. Scozziero
Author-email: sgscozziero@gmail.com
Classifier: Programming Language :: Python :: 3
Classifier: License :: OSI Approved :: GNU General Public License v3 (GPLv3)
Classifier: Operating System :: POSIX :: Linux
License-File: LICENSE
Requires-Dist: numpy
Requires-Dist: scipy
Requires-Dist: matplotlib
Requires-Dist: emcee
Requires-Dist: corner
